MANIFEST.in
README.rst
setup.py
test_web.db
groundwork_users/__init__.py
groundwork_users/version.py
groundwork_users.egg-info/PKG-INFO
groundwork_users.egg-info/SOURCES.txt
groundwork_users.egg-info/dependency_links.txt
groundwork_users.egg-info/entry_points.txt
groundwork_users.egg-info/requires.txt
groundwork_users.egg-info/top_level.txt
groundwork_users/applications/__init__.py
groundwork_users/patterns/__init__.py
groundwork_users/patterns/gw_users_pattern/__init__.py
groundwork_users/patterns/gw_users_pattern/apikeys.py
groundwork_users/patterns/gw_users_pattern/domains.py
groundwork_users/patterns/gw_users_pattern/groups.py
groundwork_users/patterns/gw_users_pattern/gw_users_pattern.py
groundwork_users/patterns/gw_users_pattern/permissions.py
groundwork_users/patterns/gw_users_pattern/roles.py
groundwork_users/patterns/gw_users_pattern/users.py
groundwork_users/patterns/gw_users_pattern/db/__init__.py
groundwork_users/patterns/gw_users_pattern/db/models.py
groundwork_users/plugins/__init__.py
groundwork_users/plugins/gw_users_cli_manager/__init__.py
groundwork_users/plugins/gw_users_web_manager/__init__.py
groundwork_users/plugins/gw_users_web_manager/gw_users_web_manager.py
groundwork_users/plugins/gw_users_web_manager/forms/__init__.py
groundwork_users/plugins/gw_users_web_manager/forms/apikey.py
groundwork_users/plugins/gw_users_web_manager/forms/domain.py
groundwork_users/plugins/gw_users_web_manager/forms/group.py
groundwork_users/plugins/gw_users_web_manager/forms/role.py
groundwork_users/plugins/gw_users_web_manager/forms/user.py
groundwork_users/plugins/gw_users_web_manager/templates/apikey_add.html
groundwork_users/plugins/gw_users_web_manager/templates/apikey_detail.html
groundwork_users/plugins/gw_users_web_manager/templates/apikey_edit.html
groundwork_users/plugins/gw_users_web_manager/templates/apikey_overview.html
groundwork_users/plugins/gw_users_web_manager/templates/domain_add.html
groundwork_users/plugins/gw_users_web_manager/templates/domain_detail.html
groundwork_users/plugins/gw_users_web_manager/templates/domain_edit.html
groundwork_users/plugins/gw_users_web_manager/templates/domain_overview.html
groundwork_users/plugins/gw_users_web_manager/templates/group_add.html
