Metadata-Version: 1.1
Name: groundwork-users
Version: 0.1.3
Summary: Plugins and Patterns for managing users inside a groundwork application
Home-page: http://groundwork-users.readthedocs.io
Author: team useblocks
Author-email: groundwork@useblocks.com
License: MIT license
Platform: any
Classifier: Development Status :: 3 - Alpha
Classifier: Environment :: Console
Classifier: Intended Audience :: Developers
Classifier: License :: OSI Approved :: MIT License
Classifier: Operating System :: OS Independent
Classifier: Programming Language :: Python
Classifier: Programming Language :: Python :: 3
Classifier: Programming Language :: Python :: 3.4
Classifier: Programming Language :: Python :: 3.5
Classifier: Programming Language :: Python :: 3.6
